PayPaython_mobile/__init__.py
PayPaython_mobile/main.py
PayPaython_mobile-2.4.1.dist-info/METADATA
PayPaython_mobile-2.4.1.dist-info/WHEEL
PayPaython_mobile-2.4.1.dist-info/top_level.txt
PayPaython_mobile-2.4.1.dist-info/RECORD
