Metadata-Version: 2.1
Name: PayPaython-mobile
Version: 2.4.1
Summary: An API wrapper for the PayPayAPI
Home-page: https://github.com/taka-4602/PayPaython-mobile
Author: taka4602
Author-email: takaka4602@gmail.com
Keywords: paypay
Classifier: Programming Language :: Python :: 3
Classifier: License :: OSI Approved :: MIT License
Classifier: Operating System :: OS Independent
Requires-Python: >=3.6
Requires-Dist: requests
Requires-Dist: pkce
